today/__init__.py
today/constants.py
today/main.py
today_calender-0.0.5.dist-info/METADATA
today_calender-0.0.5.dist-info/WHEEL
today_calender-0.0.5.dist-info/entry_points.txt
today_calender-0.0.5.dist-info/top_level.txt
today_calender-0.0.5.dist-info/RECORD
